CHANGELOG.md
LICENSE
MANIFEST.in
README.md
pyproject.toml
setup.py
daschlab/__init__.py
daschlab/apiclient.py
daschlab/cutouts.py
daschlab/exposures.py
daschlab/extracts.py
daschlab/lightcurves.py
daschlab/mosaics.py
daschlab/photometry.py
daschlab/query.py
daschlab/refcat.py
daschlab/series.py
daschlab/timeutil.py
daschlab.egg-info/PKG-INFO
daschlab.egg-info/SOURCES.txt
daschlab.egg-info/dependency_links.txt
daschlab.egg-info/requires.txt
daschlab.egg-info/top_level.txt
docs/.gitignore
docs/Makefile
docs/clear-automodapis.sh
docs/conf.py
docs/index.rst
docs/_static/copybutton.js
docs/_templates/layout.html
docs/api/daschlab.InteractiveError.rst
docs/api/daschlab.Session.rst
docs/api/daschlab.cutouts.rst
docs/api/daschlab.exposures.ExposureRow.rst
docs/api/daschlab.exposures.ExposureSelector.rst
docs/api/daschlab.exposures.Exposures.rst
docs/api/daschlab.exposures.rst
docs/api/daschlab.extracts.Extract.rst
docs/api/daschlab.extracts.rst
docs/api/daschlab.get_concept_doi.rst
docs/api/daschlab.get_version_doi.rst
docs/api/daschlab.lightcurves.Lightcurve.rst
docs/api/daschlab.lightcurves.LightcurveSelector.rst
docs/api/daschlab.lightcurves.merge.rst
docs/api/daschlab.lightcurves.rst
docs/api/daschlab.open_session.rst
docs/api/daschlab.photometry.AFlags.rst
docs/api/daschlab.photometry.BFlags.rst
docs/api/daschlab.photometry.LocalBinRejectFlags.rst
docs/api/daschlab.photometry.Photometry.rst
docs/api/daschlab.photometry.PhotometryPoint.rst
docs/api/daschlab.photometry.PhotometrySelector.rst
docs/api/daschlab.photometry.PlateQualityFlags.rst
docs/api/daschlab.photometry.rst
docs/api/daschlab.query.SessionQuery.rst
docs/api/daschlab.query.rst
docs/api/daschlab.refcat.RefcatSourceRow.rst
docs/api/daschlab.refcat.RefcatSources.rst
docs/api/daschlab.refcat.rst
docs/api/daschlab.rst
docs/api/daschlab.series.SeriesInfo.rst
docs/api/daschlab.series.SeriesKind.rst
docs/api/daschlab.series.rst
docs/api/daschlab.source_name_to_fs_name.rst